d8s_timer/__init__.py
d8s_timer/timer.py
d8s_timer/timer_temp_utils.py
tests/__init__.py
tests/test_timer.py
d8s_timer-0.5.0.dist-info/COPYING
d8s_timer-0.5.0.dist-info/COPYING.LESSER
d8s_timer-0.5.0.dist-info/METADATA
d8s_timer-0.5.0.dist-info/WHEEL
d8s_timer-0.5.0.dist-info/top_level.txt
d8s_timer-0.5.0.dist-info/zip-safe
d8s_timer-0.5.0.dist-info/RECORD
